{
  "minecraft:recipes/decorations/crafting_table": {
    "criteria": {
      "unlock_right_away": "2025-06-26 23:36:55 +0000"
    },
    "done": true
  },
  "minecraft:adventure/adventuring_time": {
    "criteria": {
      "minecraft:taiga": "2025-07-02 21:09:41 +0000",
      "minecraft:frozen_river": "2025-07-02 21:09:16 +0000",
      "minecraft:birch_forest": "2025-07-02 21:11:36 +0000",
      "minecraft:dark_forest": "2025-07-03 01:32:08 +0000",
      "minecraft:sparse_jungle": "2025-07-03 01:34:51 +0000",
      "minecraft:river": "2025-06-26 23:50:28 +0000",
      "minecraft:snowy_plains": "2025-07-02 21:07:03 +0000",
      "minecraft:snowy_taiga": "2025-07-02 21:09:31 +0000",
      "minecraft:forest": "2025-07-03 01:34:55 +0000",
      "minecraft:jungle": "2025-07-03 01:34:56 +0000",
      "minecraft:old_growth_birch_forest": "2025-07-03 01:32:10 +0000",
      "minecraft:plains": "2025-06-26 23:36:56 +0000"
    },
    "done": false
  },
  "minecraft:recipes/misc/charcoal": {
    "criteria": {
      "has_log": "2025-06-26 23:39:37 +0000"
    },
    "done": true
  },
  "minecraft:recipes/building_blocks/oak_planks": {
    "criteria": {
      "has_logs": "2025-06-26 23:39:37 +0000"
    },
    "done": true
  },
  "minecraft:recipes/building_blocks/oak_wood": {
    "criteria": {
      "has_log": "2025-06-26 23:39:37 +0000"
    },
    "done": true
  },
  "minecraft:recipes/decorations/ladder": {
    "criteria": {
      "has_stick": "2025-06-26 23:40:55 +0000"
    },
    "done": true
  },
  "minecraft:recipes/decorations/campfire": {
    "criteria": {
      "has_stick": "2025-06-26 23:40:55 +0000"
    },
    "done": true
  },
  "minecraft:recipes/tools/wooden_hoe": {
    "criteria": {
      "has_stick": "2025-06-26 23:40:55 +0000"
    },
    "done": true
  },
  "minecraft:recipes/tools/wooden_pickaxe": {
    "criteria": {
      "has_stick": "2025-06-26 23:40:55 +0000"
    },
    "done": true
  },
  "minecraft:recipes/tools/wooden_axe": {
    "criteria": {
      "has_stick": "2025-06-26 23:40:55 +0000"
    },
    "done": true
  },
  "minecraft:recipes/tools/wooden_shovel": {
    "criteria": {
      "has_stick": "2025-06-26 23:40:55 +0000"
    },
    "done": true
  },
  "minecraft:recipes/combat/wooden_sword": {
    "criteria": {
      "has_stick": "2025-06-26 23:40:55 +0000"
    },
    "done": true
  },
  "minecraft:recipes/food/cooked_beef_from_smoking": {
    "criteria": {
      "has_beef": "2025-06-26 23:42:45 +0000"
    },
    "done": true
  },
  "minecraft:adventure/root": {
    "criteria": {
      "killed_something": "2025-06-26 23:42:45 +0000"
    },
    "done": true
  },
  "minecraft:recipes/food/cooked_beef": {
    "criteria": {
      "has_beef": "2025-06-26 23:42:45 +0000"
    },
    "done": true
  },
  "minecraft:recipes/food/cooked_beef_from_campfire_cooking": {
    "criteria": {
      "has_beef": "2025-06-26 23:42:45 +0000"
    },
    "done": true
  },
  "minecraft:recipes/tools/flint_and_steel": {
    "criteria": {
      "has_obsidian": "2025-06-26 23:50:30 +0000"
    },
    "done": true
  },
  "minecraft:story/form_obsidian": {
    "criteria": {
      "obsidian": "2025-06-26 23:50:30 +0000"
    },
    "done": true
  },
  "minecraft:recipes/decorations/enchanting_table": {
    "criteria": {
      "has_obsidian": "2025-06-26 23:50:30 +0000"
    },
    "done": true
  },
  "minecraft:recipes/decorations/fletching_table": {
    "criteria": {
      "has_flint": "2025-06-26 23:53:06 +0000"
    },
    "done": true
  },
  "minecraft:recipes/combat/arrow": {
    "criteria": {
      "has_flint": "2025-06-26 23:53:06 +0000"
    },
    "done": true
  },
  "minecraft:recipes/misc/gold_ingot_from_nuggets": {
    "criteria": {
      "has_gold_nugget": "2025-06-26 23:53:07 +0000"
    },
    "done": true
  },
  "minecraft:recipes/brewing/golden_carrot": {
    "criteria": {
      "has_gold_nugget": "2025-06-26 23:53:07 +0000"
    },
    "done": true
  },
  "minecraft:recipes/misc/gold_nugget_from_smelting": {
    "criteria": {
      "has_golden_helmet": "2025-06-26 23:53:09 +0000"
    },
    "done": true
  },
  "minecraft:recipes/misc/gold_nugget_from_blasting": {
    "criteria": {
      "has_golden_helmet": "2025-06-26 23:53:09 +0000"
    },
    "done": true
  },
  "minecraft:recipes/decorations/chest": {
    "criteria": {
      "has_lots_of_items": "2025-06-26 23:53:32 +0000"
    },
    "done": true
  },
  "minecraft:recipes/misc/yellow_dye_from_dandelion": {
    "criteria": {
      "has_dandelion": "2025-06-26 23:53:38 +0000"
    },
    "done": true
  },
  "minecraft:recipes/misc/blue_dye_from_cornflower": {
    "criteria": {
      "has_cornflower": "2025-06-26 23:53:39 +0000"
    },
    "done": true
  },
  "minecraft:recipes/building_blocks/jungle_wood": {
    "criteria": {
      "has_log": "2025-07-02 21:07:18 +0000"
    },
    "done": true
  },
  "minecraft:recipes/building_blocks/jungle_planks": {
    "criteria": {
      "has_logs": "2025-07-02 21:07:18 +0000"
    },
    "done": true
  },
  "minecraft:recipes/transportation/mangrove_boat": {
    "criteria": {
      "in_water": "2025-07-03 01:32:03 +0000"
    },
    "done": true
  },
  "minecraft:recipes/transportation/acacia_boat": {
    "criteria": {
      "in_water": "2025-07-03 01:32:03 +0000"
    },
    "done": true
  },
  "minecraft:recipes/transportation/cherry_boat": {
    "criteria": {
      "in_water": "2025-07-03 01:32:03 +0000"
    },
    "done": true
  },
  "minecraft:recipes/transportation/bamboo_raft": {
    "criteria": {
      "in_water": "2025-07-03 01:32:03 +0000"
    },
    "done": true
  },
  "minecraft:recipes/transportation/spruce_boat": {
    "criteria": {
      "in_water": "2025-07-03 01:32:03 +0000"
    },
    "done": true
  },
  "minecraft:recipes/transportation/birch_boat": {
    "criteria": {
      "in_water": "2025-07-03 01:32:03 +0000"
    },
    "done": true
  },
  "minecraft:recipes/transportation/oak_boat": {
    "criteria": {
      "in_water": "2025-07-03 01:32:03 +0000"
    },
    "done": true
  },
  "minecraft:recipes/transportation/jungle_boat": {
    "criteria": {
      "in_water": "2025-07-03 01:32:03 +0000"
    },
    "done": true
  },
  "minecraft:recipes/transportation/dark_oak_boat": {
    "criteria": {
      "in_water": "2025-07-03 01:32:03 +0000"
    },
    "done": true
  },
  "minecraft:recipes/building_blocks/smooth_quartz_slab_from_smooth_quartz_stonecutting": {
    "criteria": {
      "has_smooth_quartz": "2025-07-03 01:44:22 +0000"
    },
    "done": true
  },
  "minecraft:recipes/building_blocks/smooth_quartz_slab": {
    "criteria": {
      "has_smooth_quartz": "2025-07-03 01:44:22 +0000"
    },
    "done": true
  },
  "minecraft:recipes/misc/red_dye_from_poppy": {
    "criteria": {
      "has_poppy": "2025-07-03 01:47:25 +0000"
    },
    "done": true
  },
  "minecraft:recipes/building_blocks/smooth_quartz_stairs": {
    "criteria": {
      "has_smooth_quartz": "2025-07-03 01:44:22 +0000"
    },
    "done": true
  },
  "minecraft:recipes/building_blocks/smooth_quartz_stairs_from_smooth_quartz_stonecutting": {
    "criteria": {
      "has_smooth_quartz": "2025-07-03 01:44:22 +0000"
    },
    "done": true
  },
  "DataVersion": 3465
}